Metadata-Version: 1.2
Name: SitkMetrics
Version: 1.0
Summary: A library for calculating image segmentation metrics using SimpleITK
Home-page: https://github.com/pakzaban/SitkMetrics
Author: Peyman Pakzaban
Author-email: pakzaban@gmail.com
License: UNKNOWN
Platform: UNKNOWN
Classifier: Programming Language :: Python :: 3
Classifier: License :: OSI Approved :: MIT License
Classifier: Operating System :: OS Independent
Requires-Python: >=3.6
